Metadata-Version: 2.1
Name: chromium-binary-lambda
Version: 1.0.4
Summary: Binary of chromium for usin in lambda functions
Home-page: https://github.com/fabricioadenir/chromium-binary-lambda
Author: Fabricio Silva
Author-email: fabricioadenir@gmail.com
License: UNKNOWN
Project-URL: Bug Tracker, https://github.com/fabricioadenir/chromium-binary-lambda/issues
Project-URL: repository, https://github.com/fabricioadenir/chromium-binary-lambda
Platform: UNKNOWN
Classifier: Programming Language :: Python :: 3
Classifier: License :: OSI Approved :: MIT License
Classifier: Operating System :: OS Independent
Requires-Python: >=3.8
